stripeterminal/__init__.py
stripeterminal/tests.py
stripeterminal-0.1.dist-info/LICENSE
stripeterminal-0.1.dist-info/METADATA
stripeterminal-0.1.dist-info/WHEEL
stripeterminal-0.1.dist-info/top_level.txt
stripeterminal-0.1.dist-info/RECORD
